{
    "description": "Get an Alert from IR-Flow",
    "enabled": true,
    "entry_point": "get_alert.py",
    "name": "get_alert",
    "parameters": {
        "alert_num": {
            "description": "IR-Flow Alert Number to get",
            "required": true,
            "type": "integer"
        },
        "credential_name": {
            "description": "Name of credentials from this pack's configuration to use, which includes hostname and api creds.",
            "required": true,
            "type": "string"
        }
    },
    "runner_type": "python-script"
}
