{
    "description": "Returns list of all XPU's",
    "enabled": true,
    "entry_point": "run.py",
    "name": "get_signatures_xpu_directory",
    "parameters": {
        "body_args": {
            "default": "[]",
            "description": "the body argument names",
            "immutable": true,
            "type": "string"
        },
        "endpoint": {
            "default": "/signatures/xpu/directory",
            "description": "the endpoint to use",
            "immutable": true,
            "type": "string"
        },
        "method": {
            "default": "GET",
            "description": "the HTTP method to use",
            "immutable": true,
            "type": "string"
        }
    },
    "runner_type": "python-script"
}
